eq_lexers/__init__.py
eq_lexers/eqcommand_lexer.py
eq_lexers-0.1.2.dist-info/METADATA
eq_lexers-0.1.2.dist-info/WHEEL
eq_lexers-0.1.2.dist-info/entry_points.txt
eq_lexers-0.1.2.dist-info/licenses/LICENSE.txt
eq_lexers-0.1.2.dist-info/RECORD
