Metadata-Version: 2.4
Name: eq_lexers
Version: 0.1.2
Summary: Pygments lexer for EverQuest command syntax highlighting
Project-URL: Repository, https://github.com/RedGuides/eq_lexers.git
Project-URL: Issues, https://github.com/RedGuides/eq_lexers/issues
Project-URL: Documentation, https://github.com/RedGuides/eq_lexers#readme
Author-email: Redbot <ask@redguides.com>
License-Expression: GPL-3.0-or-later
License-File: LICENSE.txt
Classifier: Development Status :: 5 - Production/Stable
Classifier: Intended Audience :: Developers
Classifier: License :: OSI Approved :: GNU General Public License v3 or later (GPLv3+)
Classifier: Operating System :: OS Independent
Classifier: Programming Language :: Python :: 3
Classifier: Topic :: Text Processing :: Markup
Requires-Dist: pygments>=2.0
